ahoy_dtu_webthing/__init__.py
ahoy_dtu_webthing/app.py
ahoy_dtu_webthing/dtu.py
ahoy_dtu_webthing/dtu_webthing.py
ahoy_dtu_webthing-1.2.22.dist-info/LICENSE
ahoy_dtu_webthing-1.2.22.dist-info/METADATA
ahoy_dtu_webthing-1.2.22.dist-info/WHEEL
ahoy_dtu_webthing-1.2.22.dist-info/entry_points.txt
ahoy_dtu_webthing-1.2.22.dist-info/top_level.txt
ahoy_dtu_webthing-1.2.22.dist-info/RECORD
