Metadata-Version: 2.1
Name: ahoy-dtu-webthing
Version: 1.2.22
Summary: Ahoy DTU webthing
Author: Gregor Roth
Author-email: gregor.roth@web.de
Requires-Python: >=3.8
License-File: LICENSE
Requires-Dist: requests >=2.31.0
Requires-Dist: webthing >=0.15.0
Requires-Dist: importlib-metadata
Requires-Dist: redzoo
